{
  "echoes": {
    "color": {
      "background": {
        "neutral": {
          "type": "color",
          "value": "{echoes.color.grey.500}"
        },
        "neutral-bolder": {
          "type": "color",
          "value": "{echoes.color.grey.400}"
        },
        "default": {
          "type": "color",
          "value": "{echoes.color.grey.600}"
        },
        "default-hover": {
          "type": "color",
          "value": "{echoes.color.grey.700}"
        },
        "default-active": {
          "type": "color",
          "value": "{echoes.color.grey.800}"
        },
        "default-disabled": {
          "type": "color",
          "value": "{echoes.color.grey.500}"
        },
        "page": {
          "type": "color",
          "value": "{echoes.color.grey.700}"
        },
        "emphasize": {
          "type": "color",
          "value": "{echoes.color.grey.700}"
        },
        "inverse": {
          "type": "color",
          "value": "{echoes.color.grey.100}"
        },
        "disabled": {
          "type": "color",
          "value": "{echoes.color.grey.500}"
        },
        "accent": {
          "default": {
            "type": "color",
            "value": "{echoes.color.indigo.300}"
          },
          "hover": {
            "type": "color",
            "value": "{echoes.color.indigo.200}"
          },
          "active": {
            "type": "color",
            "value": "{echoes.color.indigo.100}"
          },
          "focus": {
            "value": "{echoes.color.indigo.300}",
            "type": "color"
          }
        },
        "accent-weak": {
          "default": {
            "type": "color",
            "value": "#5D6CD033"
          },
          "hover": {
            "type": "color",
            "value": "#5D6CD04D"
          },
          "active": {
            "type": "color",
            "value": "#5D6CD04D"
          },
          "focus": {
            "value": "#5D6CD033",
            "type": "color"
          }
        },
        "warning": {
          "default": {
            "type": "color",
            "value": "{echoes.color.yellow.200}"
          },
          "weak": {
            "type": "color",
            "value": "#FADC7933"
          }
        },
        "success": {
          "default": {
            "type": "color",
            "value": "{echoes.color.yellowGreen.200}"
          },
          "weak": {
            "type": "color",
            "value": "#C5E67C33"
          }
        },
        "danger": {
          "default": {
            "type": "color",
            "value": "{echoes.color.red.300}"
          },
          "hover": {
            "type": "color",
            "value": "{echoes.color.red.200}"
          },
          "active": {
            "type": "color",
            "value": "{echoes.color.red.100}"
          },
          "focus": {
            "type": "color",
            "value": "{echoes.color.red.300}"
          }
        },
        "danger-weak": {
          "default": {
            "type": "color",
            "value": "#FDA29B33"
          },
          "hover": {
            "type": "color",
            "value": "{echoes.color.grey.700}"
          },
          "active": {
            "type": "color",
            "value": "{echoes.color.grey.700}"
          },
          "focus": {
            "value": "{echoes.color.red.300}",
            "type": "color"
          }
        },
        "info": {
          "default": {
            "type": "color",
            "value": "{echoes.color.blue.200}"
          },
          "weak": {
            "type": "color",
            "value": "#8FCAEA33"
          }
        },
        "transparent": {
          "type": "color",
          "value": "{echoes.color.support.transparent}"
        },
        "selected": {
          "weak": {
            "default": {
              "value": "#5D6CD033",
              "type": "color"
            },
            "hover": {
              "value": "#5D6CD04D",
              "type": "color"
            },
            "pressed": {
              "value": "#5D6CD04D",
              "type": "color"
            }
          },
          "bold": {
            "default": {
              "value": "{echoes.color.indigo.200}",
              "type": "color"
            },
            "hover": {
              "value": "{echoes.color.indigo.100}",
              "type": "color"
            },
            "pressed": {
              "value": "{echoes.color.indigo.50}",
              "type": "color"
            }
          }
        },
        "ghost": {
          "accent": {
            "default": {
              "value": "{echoes.color.background.transparent}",
              "type": "color"
            },
            "hover": {
              "value": "{echoes.color.indigo.500}",
              "type": "color",
              "$extensions": {
                "studio.tokens": {
                  "modify": {
                    "type": "alpha",
                    "value": "0.2",
                    "space": "hsl"
                  }
                }
              }
            },
            "active": {
              "value": "{echoes.color.indigo.500}",
              "type": "color",
              "$extensions": {
                "studio.tokens": {
                  "modify": {
                    "type": "alpha",
                    "value": "0.3",
                    "space": "hsl"
                  }
                }
              }
            },
            "focus": {
              "value": "{echoes.color.background.transparent}",
              "type": "color"
            }
          },
          "neutral": {
            "default": {
              "value": "{echoes.color.background.transparent}",
              "type": "color"
            },
            "hover": {
              "value": "{echoes.color.grey.700}",
              "type": "color"
            },
            "active": {
              "value": "{echoes.color.grey.800}",
              "type": "color"
            },
            "focus": {
              "value": "{echoes.color.background.transparent}",
              "type": "color"
            }
          },
          "danger": {
            "default": {
              "value": "{echoes.color.background.transparent}",
              "type": "color"
            },
            "hover": {
              "value": "{echoes.color.red.900}",
              "type": "color",
              "$extensions": {
                "studio.tokens": {
                  "modify": {
                    "type": "alpha",
                    "value": "0.2",
                    "space": "hsl"
                  }
                }
              }
            },
            "active": {
              "value": "{echoes.color.red.900}",
              "type": "color",
              "$extensions": {
                "studio.tokens": {
                  "modify": {
                    "type": "alpha",
                    "value": "0.3",
                    "space": "hsl"
                  }
                }
              }
            },
            "focus": {
              "value": "{echoes.color.background.transparent}",
              "type": "color"
            }
          }
        }
      },
      "text": {
        "bold": {
          "type": "color",
          "value": "{echoes.color.grey.25}"
        },
        "default": {
          "type": "color",
          "value": "{echoes.color.grey.100}"
        },
        "subdued": {
          "type": "color",
          "value": "{echoes.color.grey.200}"
        },
        "disabled": {
          "type": "color",
          "value": "{echoes.color.grey.400}"
        },
        "accent": {
          "type": "color",
          "value": "{echoes.color.indigo.300}"
        },
        "accent-hover": {
          "type": "color",
          "value": "{echoes.color.indigo.200}"
        },
        "accent-bold": {
          "type": "color",
          "value": "{echoes.color.indigo.50}"
        },
        "danger": {
          "type": "color",
          "value": "{echoes.color.red.300}"
        },
        "danger-bold": {
          "type": "color",
          "value": "{echoes.color.red.50}"
        },
        "warning": {
          "type": "color",
          "value": "{echoes.color.yellow.300}"
        },
        "warning-bold": {
          "type": "color",
          "value": "{echoes.color.yellow.50}"
        },
        "success": {
          "type": "color",
          "value": "{echoes.color.yellowGreen.300}"
        },
        "success-bold": {
          "type": "color",
          "value": "{echoes.color.yellowGreen.50}"
        },
        "info": {
          "type": "color",
          "value": "{echoes.color.blue.300}"
        },
        "info-bold": {
          "type": "color",
          "value": "{echoes.color.blue.50}"
        },
        "onColor": {
          "type": "color",
          "value": "{echoes.color.grey.600}"
        }
      },
      "icon": {
        "bold": {
          "type": "color",
          "value": "{echoes.color.grey.25}"
        },
        "default": {
          "type": "color",
          "value": "{echoes.color.grey.100}"
        },
        "subdued": {
          "type": "color",
          "value": "{echoes.color.grey.200}"
        },
        "disabled": {
          "type": "color",
          "value": "{echoes.color.grey.400}"
        },
        "accent": {
          "type": "color",
          "value": "{echoes.color.indigo.200}"
        },
        "danger": {
          "type": "color",
          "value": "{echoes.color.red.300}"
        },
        "warning": {
          "type": "color",
          "value": "{echoes.color.yellow.200}"
        },
        "success": {
          "type": "color",
          "value": "{echoes.color.yellowGreen.200}"
        },
        "info": {
          "type": "color",
          "value": "{echoes.color.blue.200}"
        },
        "onColor": {
          "type": "color",
          "value": "{echoes.color.grey.600}"
        },
        "selected": {
          "value": "{echoes.color.indigo.200}",
          "type": "color"
        }
      },
      "border": {
        "bolder": {
          "value": "{echoes.color.grey.200}",
          "type": "color"
        },
        "bold": {
          "value": "{echoes.color.grey.300}",
          "type": "color"
        },
        "weak": {
          "type": "color",
          "value": "{echoes.color.grey.400}"
        },
        "weaker": {
          "type": "color",
          "value": "{echoes.color.grey.500}"
        },
        "disabled": {
          "type": "color",
          "value": "{echoes.color.grey.400}"
        },
        "accent": {
          "type": "color",
          "value": "{echoes.color.indigo.200}"
        },
        "danger": {
          "type": "color",
          "value": "{echoes.color.red.300}"
        },
        "none": {
          "type": "color",
          "value": "{echoes.color.support.transparent}"
        },
        "success": {
          "type": "color",
          "value": "{echoes.color.green.300}"
        },
        "warning": {
          "type": "color",
          "value": "{echoes.color.yellow.300}"
        },
        "info": {
          "type": "color",
          "value": "{echoes.color.blue.300}"
        }
      },
      "focus": {
        "default": {
          "value": "{echoes.color.indigo.200}",
          "type": "color"
        }
      }
    },
    "boxShadow": {
      "xsmall": {
        "value": {
          "x": "0",
          "y": "1",
          "blur": "4",
          "spread": "0",
          "color": "rgba(8,9,12,0.4)",
          "type": "dropShadow"
        },
        "type": "boxShadow"
      },
      "small": {
        "value": [
          {
            "x": "0",
            "y": "1",
            "blur": "10",
            "spread": "0",
            "color": "rgba(8,9,12,0.4)",
            "type": "dropShadow"
          },
          {
            "x": "0",
            "y": "1",
            "blur": "3",
            "spread": "0",
            "color": "rgba(8,9,12,0.4)",
            "type": "dropShadow"
          }
        ],
        "type": "boxShadow"
      },
      "medium": {
        "value": [
          {
            "x": "0",
            "y": "2",
            "blur": "15",
            "spread": "-2",
            "color": "rgba(8,9,12,0.06)",
            "type": "innerShadow"
          },
          {
            "x": "0",
            "y": "4",
            "blur": "15",
            "spread": "-2",
            "color": "rgba(8,9,12,0.5)",
            "type": "dropShadow"
          }
        ],
        "type": "boxShadow"
      },
      "large": {
        "value": [
          {
            "x": "0",
            "y": "4",
            "blur": "6",
            "spread": "-2",
            "color": "rgba(8,9,12,0.05)",
            "type": "dropShadow"
          },
          {
            "x": "0",
            "y": "12",
            "blur": "20",
            "spread": "-4",
            "color": "rgba(8,9,12,0.5)",
            "type": "dropShadow"
          }
        ],
        "type": "boxShadow"
      },
      "xLarge": {
        "value": [
          {
            "x": "0",
            "y": "8",
            "blur": "8",
            "spread": "-4",
            "color": "rgba(8,9,12,0.04)",
            "type": "dropShadow"
          },
          {
            "x": "0",
            "y": "20",
            "blur": "30",
            "spread": "-4",
            "color": "rgba(8,9,12,0.5)",
            "type": "dropShadow"
          }
        ],
        "type": "boxShadow"
      }
    }
  }
}